LICENSE
MANIFEST.in
README.md
requirements.txt
setup.py
drqa/__init__.py
drqa/pipeline/__init__.py
drqa/pipeline/drqa.py
drqa/reader/__init__.py
drqa/reader/config.py
drqa/reader/data.py
drqa/reader/layers.py
drqa/reader/model.py
drqa/reader/predictor.py
drqa/reader/rnn_reader.py
drqa/reader/utils.py
drqa/reader/vector.py
drqa/retriever/__init__.py
drqa/retriever/bm25_doc_ranker.py
drqa/retriever/doc_db.py
drqa/retriever/simple.py
drqa/retriever/tfidf_doc_ranker.py
drqa/retriever/utils.py
drqa/tokenizers/__init__.py
drqa/tokenizers/corenlp_tokenizer.py
drqa/tokenizers/regexp_tokenizer.py
drqa/tokenizers/simple_tokenizer.py
drqa/tokenizers/spacy_tokenizer.py
drqa/tokenizers/tokenizer.py
drqascripts/__init__.py
drqascripts/retriever/__init__.py
drqascripts/retriever/build_bm25_lines.py
drqascripts/retriever/build_db.py
drqascripts/retriever/build_tfidf.py
drqascripts/retriever/build_tfidf_lines.py
drqascripts/retriever/eval.py
drqascripts/retriever/interactive.py
drqascripts/retriever/prep_wikipedia.py
fever_drqa.egg-info/PKG-INFO
fever_drqa.egg-info/SOURCES.txt
fever_drqa.egg-info/dependency_links.txt
fever_drqa.egg-info/requires.txt
fever_drqa.egg-info/top_level.txt