Metadata-Version: 1.2
Name: fever-drqa
Version: 1.0.13
Summary: Adapted version of Facebooks Reading Wikipedia to Answer Open-Domain Questions
Home-page: https://jamesthorne.co.uk
Author: James Thorne
Author-email: james@jamesthorne.co.uk
License: BSD License
